maryamboneh/__init__.py
maryamboneh/json2turtle.py
maryamboneh/maryam.json
maryamboneh/maryamboneh.py
maryamboneh/svg2json.py
maryamboneh/svg2turtle.py
MaryamBoneh-77.11.28.dist-info/LICENSE.md
MaryamBoneh-77.11.28.dist-info/METADATA
MaryamBoneh-77.11.28.dist-info/WHEEL
MaryamBoneh-77.11.28.dist-info/entry_points.txt
MaryamBoneh-77.11.28.dist-info/top_level.txt
MaryamBoneh-77.11.28.dist-info/RECORD
