Metadata-Version: 2.1
Name: MaryamBoneh
Version: 77.11.28
Summary: MaryamBoneh is not only a girl or a Python package, MaryamBoneh is a way of life in love and love in life. 💚
Home-page: https://github.com/SajjadAemmi/maryamboneh
Author: Sajjad Aemmi
Author-email: sajjadaemmi@gmail.com
License-File: LICENSE.md
Requires-Dist: svgpathtools
